qomo-0.0.6.dist-info/METADATA
qomo-0.0.6.dist-info/WHEEL
qomo/__init__.py
qomo/qomo.cpython-312-darwin.so
qomo-0.0.6.dist-info/RECORD
